topsis_pragya/101903503.py
Topsis_Pragya_101903503-4.0.0.dist-info/LICENSE.txt
Topsis_Pragya_101903503-4.0.0.dist-info/METADATA
Topsis_Pragya_101903503-4.0.0.dist-info/WHEEL
Topsis_Pragya_101903503-4.0.0.dist-info/top_level.txt
Topsis_Pragya_101903503-4.0.0.dist-info/RECORD
