Metadata-Version: 2.1
Name: Topsis-Pragya-101903503
Version: 4.0.0
Summary: TOPSIS PACKAGE
Home-page: UNKNOWN
Author: Pragya Nainwal
Author-email: pnainwal_be19@thapar.edu
License: UNKNOWN
Keywords: python,video,stream,video stream,camera stream,sockets
Platform: UNKNOWN
Classifier: License :: OSI Approved :: MIT License
Classifier: Programming Language :: Python :: 3
Classifier: Programming Language :: Python :: 3.7
Requires-Dist: pandas
Requires-Dist: numpy
